<archimate:ArchimateDiagramModel
    xmlns:xsi="http://www.w3.org/2001/XMLSchema-instance"
    xmlns:archimate="http://www.archimatetool.com/archimate"
    name="Referentiecomponenten en applicatiefuncties - Onderwijs"
    id="id-c7089c3afe664cb2a18c010affe9f3a8"
    documentation="Overzicht met de referentiecomponenten (soorten applicaties) die een onderwijsinstelling nodig heeft om haar processen te ondersteunen, en de applicatiefuncties die de referentiecomponenten bieden ter ondersteuning van de bedrijfsprocessen.">
  <children
      xsi:type="archimate:DiagramModelArchimateObject"
      id="id-16b9e4b4317b45b6a7849ad7eb40cf6a"
      textAlignment="1"
      fillColor="#e6f2f9">
    <bounds
        x="36"
        y="36"
        width="601"
        height="325"/>
    <children
        xsi:type="archimate:DiagramModelArchimateObject"
        id="id-f1169993f82a4e969e4c75ac7f0cb895"
        fillColor="#ffffff">
      <bounds
          x="312"
          y="24"
          width="120"
          height="55"/>
      <archimateElement
          xsi:type="archimate:ApplicationComponent"
          href="ApplicationComponent_52b06a46-94f4-4b2a-bd2a-50c39f4b0632.xml#52b06a46-94f4-4b2a-bd2a-50c39f4b0632"/>
    </children>
    <children
        xsi:type="archimate:DiagramModelArchimateObject"
        id="id-c6a0a4111be041e2a60d804d2ca31a88"
        fillColor="#ffffff">
      <bounds
          x="24"
          y="24"
          width="120"
          height="55"/>
      <archimateElement
          xsi:type="archimate:ApplicationComponent"
          href="ApplicationComponent_c64a7a54-f38e-487e-8148-01bc3d9c92fd.xml#c64a7a54-f38e-487e-8148-01bc3d9c92fd"/>
    </children>
    <children
        xsi:type="archimate:DiagramModelArchimateObject"
        id="id-1979107510e7479681efd19ec75fc06f"
        fillColor="#ffffff">
      <bounds
          x="168"
          y="24"
          width="120"
          height="55"/>
      <archimateElement
          xsi:type="archimate:ApplicationComponent"
          href="ApplicationComponent_id-6a53349c08d94fb2a24284cb913df0bb.xml#id-6a53349c08d94fb2a24284cb913df0bb"/>
    </children>
    <children
        xsi:type="archimate:DiagramModelArchimateObject"
        id="id-861477d9f12f416ebba88c8ab44b01a4"
        fillColor="#ffffff">
      <bounds
          x="456"
          y="84"
          width="120"
          height="55"/>
      <archimateElement
          xsi:type="archimate:ApplicationComponent"
          href="ApplicationComponent_3476eb2d-278a-4ecf-8931-f5d510a71b1b.xml#3476eb2d-278a-4ecf-8931-f5d510a71b1b"/>
    </children>
    <children
        xsi:type="archimate:DiagramModelArchimateObject"
        id="id-6b27b72efc30468c8238f8354e6f42dc"
        fillColor="#ffffff">
      <bounds
          x="312"
          y="84"
          width="120"
          height="55"/>
      <archimateElement
          xsi:type="archimate:ApplicationComponent"
          href="ApplicationComponent_2e2da735-1b90-47c9-87ce-b38dd7cad38d.xml#2e2da735-1b90-47c9-87ce-b38dd7cad38d"/>
    </children>
    <children
        xsi:type="archimate:DiagramModelArchimateObject"
        id="id-d6cd4ce59d2e4f2ca6fd45816ae6b0aa"
        fillColor="#ffffff">
      <bounds
          x="456"
          y="144"
          width="120"
          height="55"/>
      <archimateElement
          xsi:type="archimate:ApplicationComponent"
          href="ApplicationComponent_88714cd8-8010-4192-9231-c6da3e8a488a.xml#88714cd8-8010-4192-9231-c6da3e8a488a"/>
    </children>
    <children
        xsi:type="archimate:DiagramModelArchimateObject"
        id="id-ccbdee30b53743b5839ce24391bbcc73"
        fillColor="#ffffff">
      <bounds
          x="24"
          y="84"
          width="120"
          height="55"/>
      <archimateElement
          xsi:type="archimate:ApplicationComponent"
          href="ApplicationComponent_id-59a24c0679204eb19fc12eed6da45c9d.xml#id-59a24c0679204eb19fc12eed6da45c9d"/>
    </children>
    <children
        xsi:type="archimate:DiagramModelArchimateObject"
        id="id-e7157430083441f7964b0aaf6948c79d"
        fillColor="#ffffff">
      <bounds
          x="24"
          y="204"
          width="120"
          height="55"/>
      <archimateElement
          xsi:type="archimate:ApplicationComponent"
          href="ApplicationComponent_id-82dd361e481942eb8cb3d3e136684f79.xml#id-82dd361e481942eb8cb3d3e136684f79"/>
    </children>
    <children
        xsi:type="archimate:DiagramModelArchimateObject"
        id="id-6af83db44e0f445db80d3ba6a7a2001e"
        fillColor="#ffffff">
      <bounds
          x="24"
          y="144"
          width="120"
          height="55"/>
      <archimateElement
          xsi:type="archimate:ApplicationComponent"
          href="ApplicationComponent_id-3e7424890d834108977ce194327d01a0.xml#id-3e7424890d834108977ce194327d01a0"/>
    </children>
    <children
        xsi:type="archimate:DiagramModelArchimateObject"
        id="id-6ae919f72c5d4efc8b580db8b1f1e0ec"
        fillColor="#ffffff">
      <bounds
          x="168"
          y="144"
          width="120"
          height="55"/>
      <archimateElement
          xsi:type="archimate:ApplicationComponent"
          href="ApplicationComponent_id-3712fbc9f67c41d2be8e289fb274f068.xml#id-3712fbc9f67c41d2be8e289fb274f068"/>
    </children>
    <children
        xsi:type="archimate:DiagramModelArchimateObject"
        id="id-89f360a878734ce18c6352de2a9205c8"
        fillColor="#ffffff">
      <bounds
          x="24"
          y="264"
          width="120"
          height="55"/>
      <archimateElement
          xsi:type="archimate:ApplicationComponent"
          href="ApplicationComponent_id-a588ef5e6b6e45ed98c64dd530f3a4cd.xml#id-a588ef5e6b6e45ed98c64dd530f3a4cd"/>
    </children>
    <children
        xsi:type="archimate:DiagramModelArchimateObject"
        id="id-8d88bfcd3ede4897aeae1d47b87b37d5"
        fillColor="#ffffff">
      <bounds
          x="312"
          y="144"
          width="120"
          height="55"/>
      <archimateElement
          xsi:type="archimate:ApplicationComponent"
          href="ApplicationComponent_id-3d85d0d5dd0448f48567ca2e9326c2ce.xml#id-3d85d0d5dd0448f48567ca2e9326c2ce"/>
    </children>
    <children
        xsi:type="archimate:DiagramModelArchimateObject"
        id="id-a3f95e75ae724b8c8da6496d1aedae6d"
        fillColor="#ffffff">
      <bounds
          x="168"
          y="84"
          width="120"
          height="55"/>
      <archimateElement
          xsi:type="archimate:ApplicationComponent"
          href="ApplicationComponent_id-36325fd9bf97483bbe7bb0e4f3273732.xml#id-36325fd9bf97483bbe7bb0e4f3273732"/>
    </children>
    <children
        xsi:type="archimate:DiagramModelArchimateObject"
        id="id-624ae7b5d7dc4a51b29d396eb52d165d"
        fillColor="#ffffff">
      <bounds
          x="456"
          y="24"
          width="120"
          height="55"/>
      <archimateElement
          xsi:type="archimate:ApplicationComponent"
          href="ApplicationComponent_57051d3b-9331-4f9e-90ea-2db2f57ed44d.xml#57051d3b-9331-4f9e-90ea-2db2f57ed44d"/>
    </children>
    <children
        xsi:type="archimate:DiagramModelArchimateObject"
        id="id-ca4193b50afd459bbce7fd1015dd003e"
        fillColor="#ffffff">
      <bounds
          x="168"
          y="204"
          width="120"
          height="55"/>
      <archimateElement
          xsi:type="archimate:ApplicationComponent"
          href="ApplicationComponent_id-0990e7de4fe14a99a7b147ff8558cfce.xml#id-0990e7de4fe14a99a7b147ff8558cfce"/>
    </children>
    <children
        xsi:type="archimate:DiagramModelArchimateObject"
        id="id-495f5d8e23044c0abe0b17bdf05ad815"
        fillColor="#ffffff">
      <bounds
          x="456"
          y="204"
          width="120"
          height="55"/>
      <archimateElement
          xsi:type="archimate:ApplicationComponent"
          href="ApplicationComponent_id-0d7cd531b67f48aba854d0d0e28b0930.xml#id-0d7cd531b67f48aba854d0d0e28b0930"/>
    </children>
    <children
        xsi:type="archimate:DiagramModelArchimateObject"
        id="id-ae6adb66e77f49c1aaf277bb3ed89316"
        fillColor="#ffffff">
      <bounds
          x="312"
          y="264"
          width="120"
          height="55"/>
      <archimateElement
          xsi:type="archimate:ApplicationComponent"
          href="ApplicationComponent_id-14b9c759b744486ebbebc4cdfbc8c679.xml#id-14b9c759b744486ebbebc4cdfbc8c679"/>
    </children>
    <children
        xsi:type="archimate:DiagramModelArchimateObject"
        id="id-a7e4ceefce7a421b90b587e69202d344"
        fillColor="#ffffff">
      <bounds
          x="456"
          y="264"
          width="120"
          height="55"/>
      <archimateElement
          xsi:type="archimate:ApplicationComponent"
          href="ApplicationComponent_6baf5b4e-3e71-4461-b41f-3bd6a3f41283.xml#6baf5b4e-3e71-4461-b41f-3bd6a3f41283"/>
    </children>
    <children
        xsi:type="archimate:DiagramModelArchimateObject"
        id="id-586f37ffc9124fc9835e4c8fe2b78458"
        fillColor="#ffffff">
      <bounds
          x="168"
          y="264"
          width="120"
          height="55"/>
      <archimateElement
          xsi:type="archimate:ApplicationComponent"
          href="ApplicationComponent_id-a7792fa266d84da395bed97c1aec4303.xml#id-a7792fa266d84da395bed97c1aec4303"/>
    </children>
    <children
        xsi:type="archimate:DiagramModelArchimateObject"
        id="id-936d012b5abf4c5cba2598e25933907b"
        fillColor="#ffffff">
      <bounds
          x="312"
          y="204"
          width="120"
          height="55"/>
      <archimateElement
          xsi:type="archimate:ApplicationComponent"
          href="ApplicationComponent_50f9c743-1d1b-405b-a9a1-6f5cc79ae516.xml#50f9c743-1d1b-405b-a9a1-6f5cc79ae516"/>
    </children>
    <archimateElement
        xsi:type="archimate:Grouping"
        href="Grouping_f03e909e-e6fc-4fa2-ae6f-043144839311.xml#f03e909e-e6fc-4fa2-ae6f-043144839311"/>
  </children>
  <properties
      key="Publiceren"
      value="Niet"/>
  <properties
      key="Titel view SWC"
      value="Referentiecomponentenmodel"/>
  <properties
      key="Architectuurlaag"
      value="Applicatiearchitectuur&#xD;"/>
  <properties
      key="Domein"
      value="Niet domeingebonden"/>
  <properties
      key="Viewtype"
      value="Basis"/>
  <properties
      key="Scope"
      value="Instelling"/>
  <properties
      key="Viewdetail"
      value="Overzicht&#xD;"/>
  <properties
      key="Thema"/>
  <properties
      key="Viewpoint"
      value="Referentiecomponentenmodel"/>
  <properties
      key="Toelichting"
      value="Referentiecomponenten zijn daarmee logische groeperingen van functionaliteit die de geautomatiseerde ondersteuning bieden aan bedrijfsfuncties/-processen. Referentiecomponenten worden primair gevormd door functionaliteit die ze aanbieden en de gegevens die zij beheren. Het (hoofd)bedrijfsfunctiemodel, het informatiemodel en het referentiecomponentenmodel vormen daardoor een soort drie-eenheid die bij elkaar de meest belangrijke informatievoorzieningsaspecten beschrijven. Het referentiecomponentenmodel is meer inrichtingsafhankelijk dan de bedrijfsfunctie- en informatiemodellen. Het geeft aan welke eenheden worden voorgesteld om geautomatiseerd in te richten, waarbij de omvang van een eenheid primair wordt bepaald door de producten die beschikbaar zijn in de markt. Dit maakt het ook lastig te bepalen wat de juiste eenheid is; leveranciers bepalen vooral de omvang en trekken zich daarbij niet direct iets van andere leveranciers aan. Dat betekent dat wat de ene leverancier als één product aanbiedt (bijvoorbeeld een leerlingadministratiesysteem), door andere leveranciers als drie losse producten wordt aangeboden (inschrijfsysteem, leerlingvolgsysteem en onderwijscatalogus). Het model is een streefmodel waarbij instellingen zelf bepalen in welke mate en in welk tempo ze bewegen naar dit streefbeeld. In het algemeen moet de toepassing van het referentiecomponentenmodel vooral worden gezocht in het gebruik als vergelijkingsmateriaal met het eigen applicatielandschap van instellingen. Door te kijken waar verschillen liggen tussen het streefmodel en de huidige inrichting ontstaat een beeld van mogelijke verbeteringen. De mate waarin deze verbeteringen voldoende waarde opleveren en aansluiten bij strategische doelstellingen van de instelling kan daarbij sterk verschillen. Het resulterende plan van verschillende instellingen zal dan ook heel verschillend zijn. Het referentiecomponentenmodel geeft ook zicht op het beheer en de uitwisseling van gegevens. Per referentiecomponent is aangegeven voor welke gegevens de referentiecomponent de meest logische bron is en de andere gegevens hij nodig heeft. Dit leidt automatisch ook tot inzichten over gewenste informatiestromen en koppelvlakken tussen referentiecomponent. Zo zouden alle referentiecomponenten die een bepaald gegeven gebruiken deze moeten ophalen uit de bronreferentiecomponent. Bij het gebruik van het referentiecomponentenmodel als meetlat voor het eigen applicatielandschap zouden dus ook de informatiestromen moeten worden meegenomen. Overigens is het niet altijd mogelijk om bedrijfsobjecten eenduidig aan één applicatie toe te wijzen. Dat komt enerzijds door de omvang van de geïdentificeerde bedrijfsobjecten te groot kan zijn om aan één referentiecomponent toe te wijzen. Anderzijds doorlopen bedrijfsobjecten ook stadia waarbij verantwoordelijkheden kunnen veranderen."/>
</archimate:ArchimateDiagramModel>
